{"type":"Topology","bbox":[-61.228,14.396,-60.811,14.878],"transform":{"scale":[0.00000417004170041702,0.000004820048200481998],"translate":[-61.228,14.396]},"objects":{"centroid":{"type":"GeometryCollection","geometries":[{"type":"Point","coordinates":[69064,19502],"properties":{"ID":"97227"}},{"type":"Point","coordinates":[18705,96265],"properties":{"ID":"97215"}},{"type":"Point","coordinates":[21103,63070],"properties":{"ID":"97233"}},{"type":"Point","coordinates":[6715,87966],"properties":{"ID":"97219"}},{"type":"Point","coordinates":[18705,58921],"properties":{"ID":"97234"}},{"type":"Point","coordinates":[25899,92115],"properties":{"ID":"97203"}},{"type":"Point","coordinates":[28297,69294],"properties":{"ID":"97208"}},{"type":"Point","coordinates":[57074,46473],"properties":{"ID":"97213"}},{"type":"Point","coordinates":[37889,21577],"properties":{"ID":"97202"}},{"type":"Point","coordinates":[49880,19502],"properties":{"ID":"97206"}},{"type":"Point","coordinates":[23501,54771],"properties":{"ID":"97205"}},{"type":"Point","coordinates":[66666,71369],"properties":{"ID":"97230"}},{"type":"Point","coordinates":[88249,9129],"properties":{"ID":"97226"}},{"type":"Point","coordinates":[37889,50622],"properties":{"ID":"97209"}},{"type":"Point","coordinates":[76258,44398],"properties":{"ID":"97210"}},{"type":"Point","coordinates":[88249,17427],"properties":{"ID":"97217"}},{"type":"Point","coordinates":[42685,79667],"properties":{"ID":"97216"}},{"type":"Point","coordinates":[16307,65145],"properties":{"ID":"97204"}},{"type":"Point","coordinates":[25899,85891],"properties":{"ID":"97201"}},{"type":"Point","coordinates":[47482,65145],"properties":{"ID":"97212"}},{"type":"Point","coordinates":[30695,52697],"properties":{"ID":"97229"}},{"type":"Point","coordinates":[73860,34025],"properties":{"ID":"97223"}},{"type":"Point","coordinates":[78656,23651],"properties":{"ID":"97220"}},{"type":"Point","coordinates":[11511,94190],"properties":{"ID":"97211"}},{"type":"Point","coordinates":[25899,77593],"properties":{"ID":"97218"}},{"type":"Point","coordinates":[49880,77593],"properties":{"ID":"97228"}},{"type":"Point","coordinates":[35491,83817],"properties":{"ID":"97214"}},{"type":"Point","coordinates":[69064,56846],"properties":{"ID":"97222"}},{"type":"Point","coordinates":[88249,29875],"properties":{"ID":"97232"}},{"type":"Point","coordinates":[61870,38174],"properties":{"ID":"97207"}},{"type":"Point","coordinates":[45083,58921],"properties":{"ID":"97224"}},{"type":"Point","coordinates":[64268,27801],"properties":{"ID":"97221"}},{"type":"Point","coordinates":[13909,79667],"properties":{"ID":"97225"}},{"type":"Point","coordinates":[45083,27801],"properties":{"ID":"97231"}}]},"line":{"type":"GeometryCollection","geometries":[{"type":"LineString","arcs":[0]},{"type":"LineString","arcs":[1]},{"type":"LineString","arcs":[2]},{"type":"LineString","arcs":[3]},{"type":"LineString","arcs":[4]},{"type":"LineString","arcs":[5]},{"type":"LineString","arcs":[6]},{"type":"LineString","arcs":[7]},{"type":"LineString","arcs":[8]},{"type":"LineString","arcs":[9]},{"type":"LineString","arcs":[10]},{"type":"LineString","arcs":[11]},{"type":"LineString","arcs":[12]},{"type":"LineString","arcs":[13]},{"type":"LineString","arcs":[14]},{"type":"LineString","arcs":[15]},{"type":"LineString","arcs":[16]},{"type":"LineString","arcs":[17]},{"type":"LineString","arcs":[18]},{"type":"LineString","arcs":[19]},{"type":"LineString","arcs":[20]},{"type":"LineString","arcs":[21]},{"type":"LineString","arcs":[22]},{"type":"LineString","arcs":[23]},{"type":"LineString","arcs":[24]},{"type":"LineString","arcs":[25]},{"type":"LineString","arcs":[26]},{"type":"LineString","arcs":[27]},{"type":"LineString","arcs":[28]},{"type":"LineString","arcs":[29]},{"type":"LineString","arcs":[30]},{"type":"LineString","arcs":[31]},{"type":"LineString","arcs":[32]},{"type":"LineString","arcs":[33]},{"type":"LineString","arcs":[34]},{"type":"LineString","arcs":[35]},{"type":"LineString","arcs":[36]},{"type":"LineString","arcs":[37]},{"type":"LineString","arcs":[38]},{"type":"LineString","arcs":[39]},{"type":"LineString","arcs":[40]},{"type":"LineString","arcs":[41]},{"type":"LineString","arcs":[42]},{"type":"LineString","arcs":[43]},{"type":"LineString","arcs":[44]},{"type":"LineString","arcs":[45]},{"type":"LineString","arcs":[46]},{"type":"LineString","arcs":[47]},{"type":"LineString","arcs":[48]},{"type":"LineString","arcs":[49]},{"type":"LineString","arcs":[50]},{"type":"LineString","arcs":[51]},{"type":"LineString","arcs":[52]},{"type":"LineString","arcs":[53]},{"type":"LineString","arcs":[54]},{"type":"LineString","arcs":[55]},{"type":"LineString","arcs":[56]},{"type":"LineString","arcs":[57]},{"type":"LineString","arcs":[58]},{"type":"LineString","arcs":[59]},{"type":"LineString","arcs":[60]},{"type":"LineString","arcs":[61]},{"type":"LineString","arcs":[62]},{"type":"LineString","arcs":[63]},{"type":"LineString","arcs":[64]},{"type":"LineString","arcs":[65]},{"type":"LineString","arcs":[66]},{"type":"LineString","arcs":[67]},{"type":"LineString","arcs":[68]},{"type":"LineString","arcs":[69]},{"type":"LineString","arcs":[70]}]},"poly":{"type":"GeometryCollection","geometries":[{"type":"Polygon","arcs":[[71,0,1,2]],"properties":{"ID":"97227"}},{"type":"Polygon","arcs":[[3,72,4,5]],"properties":{"ID":"97215"}},{"type":"Polygon","arcs":[[6,7,8,9,10]],"properties":{"ID":"97233"}},{"type":"Polygon","arcs":[[-6,11,12,13,73,14]],"properties":{"ID":"97219"}},{"type":"Polygon","arcs":[[74,15,-10,16]],"properties":{"ID":"97234"}},{"type":"Polygon","arcs":[[-5,75,17,18,-12]],"properties":{"ID":"97203"}},{"type":"Polygon","arcs":[[19,20,21,22,-7,23,24,25,26]],"properties":{"ID":"97208"}},{"type":"Polygon","arcs":[[27,28,29,76,30,31,32]],"properties":{"ID":"97213"}},{"type":"Polygon","arcs":[[77,33,34]],"properties":{"ID":"97202"}},{"type":"Polygon","arcs":[[-35,35,36,-1,78]],"properties":{"ID":"97206"}},{"type":"Polygon","arcs":[[-17,-9,37,79]],"properties":{"ID":"97205"}},{"type":"Polygon","arcs":[[38,39,40,80]],"properties":{"ID":"97230"}},{"type":"Polygon","arcs":[[81,41]],"properties":{"ID":"97226"}},{"type":"Polygon","arcs":[[42,-31,82,43,-22]],"properties":{"ID":"97209"}},{"type":"Polygon","arcs":[[83,44,45,46,-29,47]],"properties":{"ID":"97210"}},{"type":"Polygon","arcs":[[84,-42,85,48,49]],"properties":{"ID":"97217"}},{"type":"Polygon","arcs":[[-27,50,51,86,52,53]],"properties":{"ID":"97216"}},{"type":"Polygon","arcs":[[-11,-16,87,54,-24]],"properties":{"ID":"97204"}},{"type":"Polygon","arcs":[[55,-13,-19,56,57]],"properties":{"ID":"97201"}},{"type":"Polygon","arcs":[[-54,58,-40,59,-33,60,-20]],"properties":{"ID":"97212"}},{"type":"Polygon","arcs":[[-38,-8,-23,-44,88]],"properties":{"ID":"97229"}},{"type":"Polygon","arcs":[[-46,61,62,63,64]],"properties":{"ID":"97223"}},{"type":"Polygon","arcs":[[-3,65,-63,66,-49,89]],"properties":{"ID":"97220"}},{"type":"Polygon","arcs":[[-15,90,-4]],"properties":{"ID":"97211"}},{"type":"Polygon","arcs":[[-58,67,-51,-26,68]],"properties":{"ID":"97218"}},{"type":"Polygon","arcs":[[-53,91,-41,-59]],"properties":{"ID":"97228"}},{"type":"Polygon","arcs":[[-52,-68,-57,-18,92]],"properties":{"ID":"97214"}},{"type":"Polygon","arcs":[[-48,-28,-60,-39,93]],"properties":{"ID":"97222"}},{"type":"Polygon","arcs":[[-45,94,-50,-67,-62]],"properties":{"ID":"97232"}},{"type":"Polygon","arcs":[[-65,69,95,-30,-47]],"properties":{"ID":"97207"}},{"type":"Polygon","arcs":[[-21,-61,-32,-43]],"properties":{"ID":"97224"}},{"type":"Polygon","arcs":[[-2,-37,70,96,-70,-64,-66]],"properties":{"ID":"97221"}},{"type":"Polygon","arcs":[[-14,-56,-69,-25,-55,97]],"properties":{"ID":"97225"}},{"type":"Polygon","arcs":[[-71,-36,-34,98]],"properties":{"ID":"97231"}}]}},"arcs":[[[58752,17842],[720,1867],[-720,2075]],[[58752,21784],[5036,0],[2398,-1037],[4317,1867],[959,2697]],[[71462,25311],[1439,-415],[-240,-1867],[1919,-1660],[1199,-3112],[479,-3112]],[[14868,87344],[480,3319],[-720,4564],[240,4565]],[[24700,99169],[-3597,-4979],[-1679,-2905],[-2158,-1659],[-1918,-2490]],[[15348,87136],[-480,208]],[[25419,67012],[2159,-3527]],[[27578,63485],[-720,-2282]],[[26858,61203],[-2158,-208]],[[24700,60995],[-3837,-207],[-3357,1037]],[[17506,61825],[-959,1867],[239,1660],[6235,1867],[2398,-207]],[[15348,87136],[239,-207]],[[15587,86929],[-239,-623]],[[15348,86306],[-10792,-4357],[-1199,-1867]],[[5755,96680],[720,-1245],[2638,-2490],[0,-1452],[1678,-2282],[4077,-1867]],[[14388,57883],[3118,3942]],[[24700,60995],[-959,-4357],[-5995,-2697]],[[34292,94812],[-3117,-4564]],[[31175,90248],[-1679,208],[-4556,-1245],[-5276,-3735],[-4077,1453]],[[35731,68672],[-1439,-415]],[[34292,68257],[240,-3527]],[[34532,64730],[-1679,-208],[-2398,-2489]],[[30455,62033],[-2877,1452]],[[25419,67012],[-2398,1245],[-3597,415],[-2158,1244]],[[17266,69916],[-719,2697],[3357,-207],[2878,207]],[[22782,72613],[1438,0],[5756,-2697],[3597,2075]],[[33573,71991],[719,-1867],[1439,-1452]],[[57314,59750],[2158,-1867],[1678,-2904],[2399,-1038],[1918,-1867],[1439,-2697]],[[66906,49377],[479,-5602]],[[67385,43775],[-2158,623],[-4077,-1037],[-959,-2283],[-1439,-415],[-2877,-2282],[-1439,-2489],[0,-1867]],[[45803,43568],[480,5602],[-960,1867]],[[45323,51037],[7914,3319],[2638,415],[0,2697]],[[55875,57468],[1439,2282]],[[36930,30083],[720,-2282],[3117,-4772]],[[40767,23029],[480,-1245],[1918,-1037],[-1918,-2490],[719,-3112],[-959,-1452],[959,-1245]],[[40767,23029],[3837,622],[2398,-1037],[1439,830],[3117,-1038],[2158,1038]],[[53716,23444],[-239,-1245],[3597,415],[1678,-830]],[[26858,61203],[2398,-4150],[-479,-3319],[-1919,-2697],[-479,-2905]],[[71462,66597],[-1439,-1452],[-9832,-2490]],[[60191,62655],[240,1245],[-2638,2904],[-2638,2075],[-4316,830],[-1439,622]],[[49400,70331],[1679,0],[1199,1245],[2638,830],[959,1245],[2158,0],[3117,2489]],[[87289,14315],[4557,1452],[5275,-207]],[[34532,64730],[2158,-1038],[-2398,-2074],[959,-2075],[-959,-1452],[5036,-2697],[1199,-2282],[4796,-2075]],[[32853,42323],[2159,4564],[-240,3320],[-3597,5602],[0,2697],[-1199,2074],[479,1453]],[[90647,39211],[-5276,-2074],[-2878,-415],[-3117,-2075]],[[79376,34647],[-720,1037],[-3837,2282],[-3357,208],[-1439,1660]],[[70023,39834],[-240,2697],[-2398,1244]],[[66906,49377],[3357,-415],[1919,415],[3836,4149],[3598,208],[479,-1037]],[[76978,12655],[1199,415],[1199,3112],[2158,2905],[2878,1660],[2877,3942]],[[87289,24689],[3597,-2283],[2398,0],[3598,-1244]],[[33573,71991],[479,622]],[[34052,72613],[5756,1660],[479,3112],[1679,6847],[1679,4564],[1678,1452]],[[50119,85684],[-4796,-3112],[-1918,-2075],[719,-2075],[-1439,-1244],[-959,-2697],[240,-2283]],[[41966,72198],[-959,-1452],[-5276,-2074]],[[11750,69916],[5516,0]],[[19184,85061],[-3836,1245]],[[31175,90248],[-720,-3527],[-1678,-1245]],[[28777,85476],[-3118,-1659],[-3837,-208],[-2638,1452]],[[41966,72198],[7434,-1867]],[[60191,62655],[-2398,-1452],[-479,-1453]],[[55875,57468],[-3118,1453],[-2877,2074],[-3118,1453],[-719,-623],[-5995,2075],[-3598,2074],[-2158,2283]],[[79376,34647],[1439,-3320]],[[80815,31327],[-960,-1867],[-3357,-830],[-3837,830]],[[72661,29460],[-1678,2075],[-3118,415],[-2158,1037]],[[65707,32987],[0,2282],[2398,1453],[1918,3112]],[[71462,25311],[1199,4149]],[[80815,31327],[1678,-2074],[3597,-1245],[1199,-3319]],[[28777,85476],[239,-3527],[1679,-1659],[240,-1660],[2878,-1452],[-480,-2282],[719,-2283]],[[22782,72613],[-3598,2490],[-2637,415],[959,2282],[2158,2075],[240,2489],[-720,2697]],[[65707,32987],[-4077,-1452],[-1439,830],[-2877,-623]],[[53716,23444],[720,4564],[-480,2075]],[[76258,15145],[-4556,-1037],[-6475,415],[-2398,1452],[-1679,-1037],[-2398,2904]],[[14868,99792],[5276,207],[4556,-830]],[[3357,80082],[-3117,4564],[-240,4150],[1199,2697],[3118,4357],[1438,830]],[[17746,53941],[-3358,3942]],[[24700,99169],[2878,-1037],[6714,-3320]],[[54436,34025],[-2158,622],[-960,1245],[720,2074],[-3118,1453],[1679,2904],[-1439,2697],[-3357,-1452]],[[41966,12448],[-2878,415],[-719,1660],[-2158,415],[-1439,1037],[719,3319],[-1678,3527],[-3118,208],[1199,3527],[2638,2282],[2398,1245]],[[58752,17842],[-2398,-3112],[-6714,2905],[-4796,-1453],[-2878,-3734]],[[26379,48132],[-4557,1453],[-719,1659],[-2638,1038],[-719,1659]],[[61150,76140],[1439,-1037],[960,-3942],[2158,0],[479,2075],[1919,1452],[2878,1245],[3117,-623],[6475,3112],[1199,1038],[3117,-1452],[-240,-2905],[-2398,1867],[-2637,-1037],[1199,-1245],[-1199,-1660],[959,-2282],[-3837,-415],[-959,1867],[-3358,1453],[-2158,-208],[-1918,-1245],[-720,-3319],[2158,-2490],[1679,208]],[[97121,15560],[1679,-2282],[-1679,-1660],[-719,-3112],[-1439,-622],[-959,-2282],[-1679,829],[-1439,-622],[240,-2490],[-1918,-2697],[-3597,-622],[-2878,1867],[-2158,3527],[2877,3320],[-1199,2074],[2398,0],[480,1660],[1918,207],[240,1660]],[[45803,43568],[-240,-2490],[-5036,1660],[-3117,0],[-4557,-415]],[[80095,52697],[-1679,207],[2399,-3942],[-1679,-1037],[0,-1452],[5515,0],[-479,-1868],[1678,-1037],[-479,-2075],[5276,-2282]],[[96882,21162],[2398,-1660],[719,-2282],[-2878,-1660]],[[87289,14315],[-479,1038],[-4077,-830],[-2638,-2905],[-1439,-415],[-1678,1452]],[[45323,90248],[3837,-2075],[959,-2489]],[[14388,57883],[-1918,2490],[-2158,4772],[1438,4771]],[[32853,42323],[-1918,2490],[-2878,2697],[-1678,622]],[[76978,12655],[-720,2490]],[[5755,96680],[5995,2697],[3118,415]],[[50119,85684],[3118,-208],[479,-2074],[2159,-2490],[5275,-4772]],[[34292,94812],[1679,-1244],[2878,-1038],[3357,-1867],[2158,830],[959,-1245]],[[71462,66597],[-719,-1867],[4316,-415],[3118,-2075],[-5756,-1452],[-4076,-3527],[3117,-3942],[2158,415],[1919,2075],[7194,0],[-959,-2490],[-1679,-622]],[[90647,39211],[959,-1245],[-1679,-1867],[2878,-622],[3597,207],[-3118,-3734],[2878,-2490],[240,-3112],[-2158,0],[-480,-2282],[2878,623],[240,-3527]],[[57314,31742],[-1919,2490],[-959,-207]],[[53956,30083],[3358,1659]],[[11750,69916],[480,2697],[-1918,2075],[-3358,2697],[-1438,2075],[-2159,622]],[[36930,30083],[2158,207],[960,1660],[5755,1037],[-720,-2904],[5516,-415],[3357,415]]]}
