{"type":"Topology","bbox":[-54.602,2.118,-51.626,5.747],"transform":{"scale":[0.00002976029760297602,0.000036290362903629036],"translate":[-54.602,2.118]},"objects":{"centroid":{"type":"GeometryCollection","geometries":[{"type":"Point","coordinates":[50470,66464],"properties":{"ID":"97358"}},{"type":"Point","coordinates":[78023,76108],"properties":{"ID":"97309"}},{"type":"Point","coordinates":[20900,78037],"properties":{"ID":"97311"}},{"type":"Point","coordinates":[70295,64535],"properties":{"ID":"97310"}},{"type":"Point","coordinates":[76679,77211],"properties":{"ID":"97302"}},{"type":"Point","coordinates":[69959,50206],"properties":{"ID":"97301"}},{"type":"Point","coordinates":[28293,23477],"properties":{"ID":"97353"}},{"type":"Point","coordinates":[60550,19895],"properties":{"ID":"97356"}},{"type":"Point","coordinates":[43078,86855],"properties":{"ID":"97303"}},{"type":"Point","coordinates":[13844,62606],"properties":{"ID":"97357"}},{"type":"Point","coordinates":[40389,49655],"properties":{"ID":"97352"}},{"type":"Point","coordinates":[53494,86028],"properties":{"ID":"97312"}},{"type":"Point","coordinates":[70295,74179],"properties":{"ID":"97313"}},{"type":"Point","coordinates":[70295,78864],"properties":{"ID":"97305"}},{"type":"Point","coordinates":[22916,98153],"properties":{"ID":"97361"}},{"type":"Point","coordinates":[11156,74731],"properties":{"ID":"97360"}},{"type":"Point","coordinates":[18884,52962],"properties":{"ID":"97362"}},{"type":"Point","coordinates":[83064,44695],"properties":{"ID":"97308"}},{"type":"Point","coordinates":[93816,57095],"properties":{"ID":"97314"}},{"type":"Point","coordinates":[76007,74731],"properties":{"ID":"97307"}},{"type":"Point","coordinates":[31989,79139],"properties":{"ID":"97306"}},{"type":"Point","coordinates":[61559,77486],"properties":{"ID":"97304"}}]},"line":{"type":"GeometryCollection","geometries":[{"type":"LineString","arcs":[0]},{"type":"LineString","arcs":[1]},{"type":"LineString","arcs":[2]},{"type":"LineString","arcs":[3]},{"type":"LineString","arcs":[4]},{"type":"LineString","arcs":[5]},{"type":"LineString","arcs":[6]},{"type":"LineString","arcs":[7]},{"type":"LineString","arcs":[8]},{"type":"LineString","arcs":[9]},{"type":"LineString","arcs":[10]},{"type":"LineString","arcs":[11]},{"type":"LineString","arcs":[12]},{"type":"LineString","arcs":[13]},{"type":"LineString","arcs":[14]},{"type":"LineString","arcs":[15]},{"type":"LineString","arcs":[16]},{"type":"LineString","arcs":[17]},{"type":"LineString","arcs":[18]},{"type":"LineString","arcs":[19]},{"type":"LineString","arcs":[20]},{"type":"LineString","arcs":[21]},{"type":"LineString","arcs":[22]},{"type":"LineString","arcs":[23]},{"type":"LineString","arcs":[24]},{"type":"LineString","arcs":[25]},{"type":"LineString","arcs":[26]},{"type":"LineString","arcs":[27]},{"type":"LineString","arcs":[28]},{"type":"LineString","arcs":[29]},{"type":"LineString","arcs":[30]},{"type":"LineString","arcs":[31]},{"type":"LineString","arcs":[32]},{"type":"LineString","arcs":[33]},{"type":"LineString","arcs":[34]},{"type":"LineString","arcs":[35]},{"type":"LineString","arcs":[36]},{"type":"LineString","arcs":[37]},{"type":"LineString","arcs":[38]},{"type":"LineString","arcs":[39]},{"type":"LineString","arcs":[40]},{"type":"LineString","arcs":[41]},{"type":"LineString","arcs":[42]}]},"poly":{"type":"GeometryCollection","geometries":[{"type":"Polygon","arcs":[[0,1,2,3,4,5,6]],"properties":{"ID":"97358"}},{"type":"Polygon","arcs":[[7,8,9,43]],"properties":{"ID":"97309"}},{"type":"Polygon","arcs":[[44,10,11,12]],"properties":{"ID":"97311"}},{"type":"Polygon","arcs":[[13,-8,45,14,-4,15,16]],"properties":{"ID":"97310"}},{"type":"Polygon","arcs":[[17,18,46,-10]],"properties":{"ID":"97302"}},{"type":"Polygon","arcs":[[-5,-15,47,19,20,21,22,23]],"properties":{"ID":"97301"}},{"type":"Polygon","arcs":[[24,25,-23,26,48]],"properties":{"ID":"97353"}},{"type":"Polygon","arcs":[[27,49,-27,-22]],"properties":{"ID":"97356"}},{"type":"Polygon","arcs":[[50,28,-1,29]],"properties":{"ID":"97303"}},{"type":"Polygon","arcs":[[30,-12,31,32,51]],"properties":{"ID":"97357"}},{"type":"Polygon","arcs":[[-24,-26,33,34,-6]],"properties":{"ID":"97352"}},{"type":"Polygon","arcs":[[-29,52,35,-2]],"properties":{"ID":"97312"}},{"type":"Polygon","arcs":[[-17,36,37,38]],"properties":{"ID":"97313"}},{"type":"Polygon","arcs":[[39,-38,40,53,-19]],"properties":{"ID":"97305"}},{"type":"Polygon","arcs":[[54,41]],"properties":{"ID":"97361"}},{"type":"Polygon","arcs":[[55,-13,-31]],"properties":{"ID":"97360"}},{"type":"Polygon","arcs":[[56,-33,-34,-25]],"properties":{"ID":"97362"}},{"type":"Polygon","arcs":[[-21,42,57,-28]],"properties":{"ID":"97308"}},{"type":"Polygon","arcs":[[-20,58,-43]],"properties":{"ID":"97314"}},{"type":"Polygon","arcs":[[-39,-40,-18,-9,-14]],"properties":{"ID":"97307"}},{"type":"Polygon","arcs":[[-30,-7,-35,-32,-11,59,-42,60]],"properties":{"ID":"97306"}},{"type":"Polygon","arcs":[[61,-41,-37,-16,-3,-36]],"properties":{"ID":"97304"}}]}},"arcs":[[[41532,77128],[739,799],[571,1020],[437,137],[639,-330],[1142,854],[134,1130],[1277,-689],[202,-276]],[[46673,79773],[1411,28],[370,303],[-168,386],[369,689],[672,27],[303,-744],[1411,-882],[202,-496],[840,55],[-101,469],[941,331],[672,-111],[1109,166],[1176,-331],[705,-441]],[[56585,79222],[-604,-358],[1176,-579],[739,-826],[437,-1020],[-773,-1268],[-303,-1405],[303,-716],[-605,-1295],[134,-634],[605,-358],[-302,-662],[504,-661],[-67,-358],[1646,-827],[34,-992],[403,28],[974,-1433]],[[60886,65858],[34,-414],[-437,-303],[-470,-964],[-1210,-469],[-269,-716],[135,-1405],[941,-882],[33,-2039],[202,-524],[-202,-551],[202,-551],[-773,-221]],[[59072,56819],[-638,-330],[33,-303],[-1646,-772],[-168,-771],[-706,-772],[-403,-937],[-1042,-138],[-336,-909],[-1478,-441],[-236,-496],[-705,165],[-571,-523],[-740,-83],[-403,-468],[-1310,-551],[-101,-248]],[[48622,49242],[-571,689],[-471,1240],[-437,688],[-336,965],[-638,248],[-403,634],[-34,771],[941,689],[168,661],[-437,386],[-202,717],[-739,303],[-168,992],[-1613,523],[-537,992],[504,496],[-571,662],[-807,110],[-235,799]],[[42036,61807],[269,661],[-135,359],[202,1184],[370,28],[571,799],[67,992],[-101,524],[403,385],[-705,1185],[-740,-27],[-2251,1763],[168,1158],[-840,303],[269,496],[-302,689],[504,551],[638,248],[0,551],[-504,468],[336,414],[571,193],[202,551],[840,496],[-168,385],[504,469],[-672,496]],[[79502,75833],[-639,-579],[-1008,-83]],[[77855,75171],[-268,83],[-740,1157]],[[76847,76411],[1176,1103]],[[20027,96444],[907,-193],[706,-771],[638,165],[437,-303],[941,-27],[336,-386],[-269,-331],[302,-606],[-571,-28],[-470,-551],[-672,-330],[470,-579],[672,-1213],[1344,-716],[605,-193],[-437,-1267],[-605,-1213],[-1344,-220],[-705,-276],[-168,-303],[-773,-55],[-907,-634],[-101,-496],[-1109,-551],[-135,-827],[-705,-275],[269,-1020],[-303,-964],[538,-551],[-336,-524],[302,-275],[571,909],[101,909],[807,0],[806,386],[403,-441],[1210,-496],[907,799],[538,-193],[739,496],[504,0],[370,-1129],[873,-276],[-235,-744],[1109,-468],[370,-744],[-605,-441],[806,-331],[-1142,-579],[571,-937],[-134,-771],[504,-717],[-269,-523],[134,-469],[437,-275],[403,-827],[101,-909],[-638,-882],[403,-248],[168,-882],[-605,-937],[874,-1047],[0,-441],[-336,-826],[0,-414],[-706,-1212],[67,-827],[504,-1350],[-336,-386],[-134,-799],[-639,-1102],[-336,-799],[101,-1626]],[[27150,59382],[-1848,524],[-235,-83],[-672,772],[-706,551],[-302,578],[0,799],[-807,1351],[-974,-331],[-605,303],[269,909],[-538,1902],[303,358],[33,579],[336,330],[-436,496]],[[20968,68420],[-68,662],[605,578],[-33,331],[604,744],[-235,331],[-873,55],[-437,-441],[-840,27],[-605,304],[-370,-111],[-1915,910],[-1075,137],[-1311,607],[-201,441],[772,744],[-235,606],[-840,330],[-201,689],[-336,331],[-303,827],[-336,358],[-806,-110],[-168,468],[-538,276],[-269,523],[202,662],[873,799],[1009,744],[134,330],[-269,882],[403,579],[1143,964],[-672,1020],[-874,441],[135,633],[-1244,524],[-269,441],[135,386],[-269,578]],[[74932,72967],[1479,-579],[873,1323],[269,1020],[302,440]],[[81854,74235],[101,-827],[-605,-827],[-168,-854],[269,-551],[-1311,-799],[-369,-469],[-269,-992],[101,-551],[571,-744],[1512,-661],[-1243,-1020],[605,-1350],[134,-579],[-806,-716],[134,-579],[-1042,359],[-907,-634],[34,-331],[-1445,-303],[-975,-882],[-134,-771],[-807,-607],[-369,221],[-706,-358],[-269,-386],[-940,-386],[-202,-275],[-2251,55],[-538,-607],[-571,83],[-437,-275],[101,-414],[-1546,-1433],[101,-385],[-1378,-552],[-840,-220],[-773,83],[-1041,496],[-941,689],[-1243,-138],[-1479,441],[-840,633]],[[60886,65858],[437,110],[370,799],[470,83],[471,689],[-202,440],[504,524],[403,-193],[538,827],[1042,909],[269,606],[369,-55],[1176,1102]],[[66733,71699],[403,-192],[706,82],[2117,-1130],[739,-55],[975,-385],[605,854],[67,551],[739,937],[0,606],[806,28],[572,-359],[470,331]],[[76847,76411],[-470,138],[-639,606]],[[75738,77155],[68,193]],[[95900,64177],[-3226,-386],[-639,-303],[101,-1681],[-336,-331],[403,-468],[-235,-606],[403,-1681],[34,-1075],[672,-55],[739,-303],[67,-496],[-739,-165],[-605,-441],[-436,220],[-1143,-220],[-33,-441],[-1042,-331],[-773,772],[-504,-386],[-638,0],[-471,-276],[-403,-992],[605,-248],[-101,-441],[571,-413],[504,-1460]],[[88675,51970],[-941,-248],[-1109,-662],[-369,496],[-1714,-964],[-168,413],[-1142,248],[-336,-275],[67,-799],[-538,-83],[-504,-992],[-672,-193],[-1008,303],[-67,-606],[-403,-193],[-303,-579],[-571,0],[-538,-909],[-2083,-496],[-1445,138],[-403,-1130],[235,-193],[-269,-1460],[68,-469],[-807,-964],[-1243,-83],[-504,-330],[-571,716],[-471,-1323],[67,-1102],[-436,-992],[-908,-882],[1008,-413]],[[70597,37944],[-436,-220],[-1244,-248],[-67,-414],[336,-413],[-336,-909],[34,-1406],[-202,-275],[-1781,-414],[-705,55],[-303,-496],[235,-633],[740,-1047],[-740,-607],[-537,-193],[-739,-606],[-303,-578],[-638,220],[-773,-138],[-773,386],[-605,83],[-336,468],[538,799],[-1008,827],[-1076,358],[-940,-716],[-1815,0],[-1042,578],[-1512,276],[-1344,-138],[-403,165],[-1176,-192],[-269,-552],[235,-496],[-470,-1267]],[[51142,30201],[-706,-55],[0,496]],[[50436,30642],[-571,909],[-941,358],[-840,1130],[605,909],[-302,882],[134,689],[1243,744],[-201,744],[-538,469],[470,992],[1042,909],[-134,1102],[537,386],[-470,413],[-739,-413],[-504,331],[336,606],[-236,1488],[-168,358],[-806,661],[-706,992],[-705,193],[-773,910],[773,248],[1478,1295],[706,110],[269,716],[-773,469]],[[16902,44833],[638,303],[336,386],[1075,193],[404,-166],[571,1047],[504,386],[403,-165],[1848,689],[639,-83],[571,992],[336,0],[168,661],[773,579],[1008,-55],[504,276],[1411,1295],[907,55]],[[28998,51226],[269,248],[1579,-276],[404,-413],[470,110],[739,-413],[538,220],[235,-661],[672,-28],[571,276],[841,-358],[-538,-441],[33,-524],[1076,-358],[537,-1102],[236,-854],[1276,-1048],[1042,-330],[1109,-1433],[-370,-524],[135,-1129],[504,-276],[537,-827],[-336,-854],[168,-689],[-201,-413],[-67,-1102],[-672,-744],[-68,-689],[840,-551],[908,82],[1545,-358],[538,-358],[1142,248],[1176,-413],[101,-166],[-369,-1570],[302,-689],[1949,-551],[202,-552],[739,-330],[773,-662],[873,-82]],[[51142,30201],[739,-524],[168,-606],[-101,-661],[-1008,-1378],[-168,-2370],[-840,-275],[-336,-662],[-1646,-661],[-303,-964],[-604,-441],[-672,-855],[235,-1184],[-874,-414],[-1546,-1598],[370,-799],[-1008,-110],[-67,-634],[168,-606],[-336,-744],[336,-607],[-907,-220],[-337,-248],[404,-606],[672,-193],[-101,-965],[-739,-551],[437,-330],[33,-662],[975,-330],[638,-772],[941,-165],[-739,-1240],[-840,-524],[-34,-661],[-874,-524]],[[70597,37944],[1143,-276],[302,-385],[1008,137],[437,-137],[34,-965],[537,-661],[1008,248],[504,-496],[1546,744],[571,27],[941,827],[538,909],[1176,414],[370,-83],[1444,331],[101,744],[941,441],[672,-28],[706,248],[873,-193],[504,-303]],[[48118,93799],[269,-579],[1243,-1240],[1848,-661],[403,-441],[-134,-1157],[-437,-441],[-202,-1185],[-470,-909],[269,-965],[336,-496],[-135,-330],[370,-607],[-874,166],[-739,1377],[-874,193],[0,-1708],[336,-606],[-33,-689],[-1680,-1378],[134,-964],[-201,-386],[-538,-55],[-336,-965]],[[41532,77128],[-1647,579],[-806,-276],[336,1460],[-269,689],[-1075,83],[-471,634],[-67,661],[-369,165],[-740,-440],[-268,275],[235,799],[369,193],[135,937],[-907,441],[168,909],[-404,441],[101,386],[538,358],[403,909],[-806,441],[-135,386],[370,1405],[-303,1075],[336,1240],[437,276],[135,937],[907,137],[605,-248],[739,-27],[235,1350],[-403,716],[-840,552],[0,413]],[[6116,68779],[571,-83],[437,303],[1646,83],[605,-303],[504,-800],[907,-275],[807,193],[403,-358],[1445,-386],[302,-248],[1915,-248],[706,248],[807,0],[336,193],[2116,275],[1345,1047]],[[27150,59382],[471,-386]],[[27621,58996],[-706,-496],[-1378,248],[-1444,-137],[-471,-166],[-1042,827],[-806,331],[-1109,192],[-1344,-82],[-773,-441],[-571,-827],[-739,-275],[-370,248],[-706,-496],[-1579,496],[-1109,854],[-907,-248],[-101,-1764],[-571,-385],[67,-304],[-873,-799],[-672,-193],[-1042,0]],[[28998,51226],[-604,606],[201,937],[-269,523],[840,441],[135,441],[-605,276],[-403,468],[201,248],[101,1378],[-235,1130],[-336,330],[-168,855],[-235,137]],[[27621,58996],[806,662],[1243,771],[773,0],[1076,248],[1243,772],[1209,1047],[605,275],[605,-165],[0,-606],[-336,-1350],[1311,-689],[772,358],[807,-358],[1008,358],[538,-220],[1377,220],[1378,1488]],[[60114,88343],[100,-827],[-537,-193],[67,-385],[-1747,-1406],[-370,-633],[0,-469],[-370,-689],[-1176,-330],[-537,-524],[-504,-165],[101,-689],[-572,-496],[471,-634],[1646,-1240],[-101,-441]],[[66733,71699],[-672,579],[67,331],[-168,1295],[303,1130],[705,330],[-470,469],[504,689],[101,606]],[[67103,77128],[1377,-303],[303,-193],[974,827],[471,606],[638,-138],[739,248],[841,-193],[-370,-441],[-336,-854],[1042,-331],[739,689],[638,-386],[672,83]],[[74831,76742],[-571,-606],[202,-496],[-236,-358],[504,-689],[-168,-358],[101,-1048],[269,-220]],[[75738,77155],[-907,-413]],[[67103,77128],[-135,854],[538,579],[235,909],[471,882],[-236,248],[-739,-55],[-201,330],[1411,1461]],[[26243,99503],[-470,-1102],[-706,-1075],[-538,-110],[-504,-1268],[-537,359],[-773,82],[-1109,937],[-706,193],[-537,-358],[-639,0]],[[88675,51970],[504,-193],[840,138],[471,-304],[605,-55],[604,-358],[672,386],[1546,-83],[370,303],[269,1185],[1142,28],[1109,771],[705,221],[168,634],[-604,110],[604,937],[1815,2039]],[[78023,77514],[572,-469],[0,-386],[907,-826]],[[11391,87020],[1176,634],[639,110],[840,551],[336,524],[873,579],[504,606],[504,882],[840,661],[975,1102],[571,303],[302,496],[639,303],[504,1433],[-67,1240]],[[79502,75833],[235,-276],[639,-27],[1478,-1295]],[[75806,77348],[336,469],[1075,248],[806,-551]],[[81854,74235],[1882,-744],[369,-386],[2722,-1461],[403,-441],[3024,-909],[639,221],[1176,-138],[974,-579],[336,-413],[773,-579],[504,-1102],[336,-1488],[-67,-854],[303,-607],[672,-578]],[[43178,6117],[-1310,221],[-101,-551],[-437,-414],[-907,-220],[-235,-413],[-907,-193],[-639,-634],[-437,-221],[-1109,193],[-1579,-165],[-773,386],[-1209,386],[-1781,0],[101,440],[-505,193],[-672,-248],[-336,441],[-1008,0],[-638,248],[739,524],[-537,964],[-807,55],[-571,-413],[-471,0],[-436,-551],[-840,-248],[739,-579],[-1311,-220],[-1041,165],[-67,-937],[-673,-386],[-336,469],[-638,-248],[-235,-1350],[-773,-28],[-336,-358],[-538,83],[-907,-744],[-974,110],[-605,275],[-639,-633],[-67,-689],[-907,-827],[-538,138],[-1041,27],[-504,359],[-538,936],[-1143,-578],[-1008,165],[-470,-331],[-1714,441],[-1411,414],[235,771],[-336,193],[-1142,-358],[-2117,303],[-1445,1268],[-638,-28],[-538,524],[202,1240],[-336,275],[-1647,-55],[-336,331],[1075,468],[1244,-413],[772,-55],[-67,633],[235,855],[1176,1185],[1042,-56],[639,138],[974,854],[67,359],[538,275],[101,496],[571,276],[302,578],[-33,634],[571,331],[370,1433],[873,937],[370,165],[504,1543],[1411,854],[471,634],[-68,331],[437,413],[-336,634],[739,303],[202,551],[-504,744],[336,882],[403,606],[-134,1020],[-269,689],[504,413],[-773,1350],[303,221],[336,909],[-370,634],[-874,-28],[-100,606],[638,1213],[672,330],[403,662],[907,992],[1177,937],[705,-166],[538,524],[67,1075],[269,303],[-168,413],[1579,1350],[-168,827],[302,303],[0,1075],[269,468],[-302,386],[134,634],[605,523],[202,772],[-874,1130],[-538,-56],[-201,-440],[-739,110],[33,496],[-1109,578],[135,882],[-672,1075]],[[85953,39487],[-1008,-1405],[-436,-276],[-269,-771],[-471,-303],[-974,-1571],[-1311,-1846],[-403,-689],[-470,-386],[-1042,-1295],[-874,331],[-504,-469],[-604,-275],[-336,-744],[134,-579],[-1008,-331],[-773,-1185],[302,-826],[572,-414],[-941,-1570],[-269,-111],[-302,-1129],[-807,-1323],[538,-413],[-370,-414],[-1008,-137],[-840,-1185],[-370,-772],[-571,-771],[-201,-1130],[-706,-854],[-941,-1654],[-907,-606],[336,-689],[437,-441],[134,-496],[-336,-386],[-773,-468],[303,-799],[-437,-138],[-672,-551],[-303,-496],[-806,-83],[67,-799],[-705,-82],[-269,-689],[-370,-331],[-168,-882],[-1646,-413],[-236,-413],[-1780,-634],[-807,-469],[-1512,-358],[-605,-303],[101,-441],[-538,-110],[-235,-606],[-806,-1075],[-1277,-248],[-34,-276],[-1545,-303],[-336,193],[-1882,386],[-941,909],[-1815,55],[-1579,-358],[-873,0],[-639,-248],[-638,221],[-605,-607],[-471,166],[168,744],[1512,1157],[-1008,165],[-100,441],[-706,414],[-672,165],[-437,441],[-101,468]],[[38071,94984],[168,110],[2050,-138],[2856,-689],[571,386],[974,221],[370,-359],[907,-137],[1546,-496],[605,-83]],[[9375,55579],[-67,414],[-538,165],[-840,551],[-706,83],[-302,634],[470,1681],[-403,1212],[269,1212],[-302,386],[-706,303],[-706,-358],[168,1433],[-336,634],[336,689],[-605,1736],[841,799],[336,1433],[-168,193]],[[48118,93799],[1310,-413],[941,-607],[1109,-468],[1882,-358],[571,138],[1747,-221],[739,-606],[605,-303],[1647,-1130],[739,-854],[67,-386],[639,-248]],[[68447,82336],[504,-138],[1747,-1323],[1277,-1129],[1949,-1323],[403,-524],[840,-661],[639,110]],[[19724,97161],[101,551],[1344,1929],[135,303],[1142,55],[1310,-386],[2487,-110]],[[6116,68779],[-605,799],[470,606],[-302,882],[201,496],[-268,275],[-807,28],[-235,386],[201,1047],[-201,1267],[-101,1819],[-336,386],[1109,854],[201,496],[-100,937],[168,826],[403,469],[302,744],[34,661],[1378,634],[336,827],[470,165],[1445,2232],[1512,1405]],[[16902,44833],[-1042,1515],[-2285,166],[-134,468],[437,524],[-269,248],[-1344,248],[-437,744],[33,606],[-974,331],[-605,744],[-235,964],[-504,827],[-605,661],[-739,358],[470,1268],[0,468],[706,606]],[[99495,57729],[504,-496],[-302,-524],[-101,-1185],[-336,-1460],[-269,-717],[-672,-496],[-2352,-964],[-1008,-689],[-202,-331],[-33,-1184],[-538,-937],[-773,-524],[-34,-248],[-1108,-716],[-605,-827],[-739,-496],[-773,-83],[-236,-413],[336,-579],[-201,-606],[-1143,-110],[-571,-413],[-437,-882],[-235,-827],[168,-413],[-1075,-965],[-807,-1157]],[[95900,64177],[-202,-634],[437,-441],[974,-551],[135,-331],[-336,-523],[0,-469],[537,-1240],[1445,-1846],[605,-413]],[[20027,96444],[-303,717]],[[26243,99503],[1142,-276],[1714,-826],[773,-221],[1277,-716],[1512,-606],[1243,-689],[303,27],[1982,-689],[1882,-523]],[[60114,88343],[806,-441],[807,-909],[1411,-1047],[1915,-1020],[336,-413],[1008,-744],[-67,-331],[706,-303],[1041,-772],[370,-27]]]}
