[
	{
		"ISO 3166-2": "ES-AN",
		"CNIG": "01",
		"NUTS": "ES61",
		"Name": "Andalucía"
	},
	{
		"ISO 3166-2": "ES-AR",
		"CNIG": "02",
		"NUTS": "ES24",
		"Name": "Aragón"
	},
	{
		"ISO 3166-2": "ES-AS",
		"CNIG": "03",
		"NUTS": "ES12",
		"Name": "Principado de Asturias"
	},
	{
		"ISO 3166-2": "ES-IB",
		"CNIG": "04",
		"NUTS": "ES53",
		"Name": "Illes Balears"
	},
	{
		"ISO 3166-2": "ES-CN",
		"CNIG": "05",
		"NUTS": "ES70",
		"Name": "Canarias"
	},
	{
		"ISO 3166-2": "ES-CB",
		"CNIG": "06",
		"NUTS": "ES13",
		"Name": "Cantabria"
	},
	{
		"ISO 3166-2": "ES-CL",
		"CNIG": "07",
		"NUTS": "ES41",
		"Name": "Castilla y León"
	},
	{
		"ISO 3166-2": "ES-CM",
		"CNIG": "08",
		"NUTS": "ES42",
		"Name": "Castilla - La Mancha"
	},
	{
		"ISO 3166-2": "ES-CT",
		"CNIG": "09",
		"NUTS": "ES51",
		"Name": "Cataluña"
	},
	{
		"ISO 3166-2": "ES-VC",
		"CNIG": "10",
		"NUTS": "ES52",
		"Name": "Comunitat Valenciana"
	},
	{
		"ISO 3166-2": "ES-EX",
		"CNIG": "11",
		"NUTS": "ES43",
		"Name": "Extremadura"
	},
	{
		"ISO 3166-2": "ES-GA",
		"CNIG": "12",
		"NUTS": "ES11",
		"Name": "Galicia"
	},
	{
		"ISO 3166-2": "ES-MD",
		"CNIG": "13",
		"NUTS": "ES30",
		"Name": "Comunidad de Madrid"
	},
	{
		"ISO 3166-2": "ES-MC",
		"CNIG": "14",
		"NUTS": "ES62",
		"Name": "Región de Murcia"
	},
	{
		"ISO 3166-2": "ES-NC",
		"CNIG": "15",
		"NUTS": "ES22",
		"Name": "Comunidad Foral de Navarra"
	},
	{
		"ISO 3166-2": "ES-PV",
		"CNIG": "16",
		"NUTS": "ES21",
		"Name": "País Vasco"
	},
	{
		"ISO 3166-2": "ES-RI",
		"CNIG": "17",
		"NUTS": "ES23",
		"Name": "La Rioja"
	},
	{
		"ISO 3166-2": "ES-CE",
		"CNIG": "18",
		"NUTS": "ES63",
		"Name": "Ceuta"
	},
	{
		"ISO 3166-2": "ES-ML",
		"CNIG": "19",
		"NUTS": "ES64",
		"Name": "Melilla"
	}
]